{"archive_write_open2": {"371220": {"disasm": ["PUSH {R4-R7LR}", "MOV R5 func", "VPUSH {D8-D11}", "MOV R4 func", "SUB SP SP imm", "LDR func [SPoffs]", "STR func [SPoffs]", "LDR func func - addr", "STR R1 [SPoffs]", "LDR R1 [SPoffs]", "ADD R3 PC R3", "STR func [SP]", "MOV func imm", "STR R1 [SPoffs]", "LDR R1 func - addr", "VLD1.64 {D8-D9} [SP@64]", "ADD R1 PC R1", "STR R1 [SPoffs]", "LDR R1 func - addr", "ADD R1 PC R1", "STR R1 [SPoffs]", "LDR R1 func - addr", "ADD R1 PC R1", "STR R1 [SPoffs]", "LDR R1 func - addr", "ADD R1 PC R1", "STR R1 [SPoffs]", "MOV R1 imm", "VLDR D10 [SPoffs]", "VLDR D11 [SPoffs]", "BL func", "CMN func imm", "BEQ addr"], "preds": [], "succs": [371356, 371600], "hash": "b2c961c1fa14f3fa7f688eee9841056e"}, "371356": {"disasm": ["MOV func a", "BL addr", "MOV R1 imm", "MOV R0 imm", "VSTR D8 [aoffs]", "VSTR D9 [aoffs]", "STR func [aoffs]", "BL addr", "SUBS R3 R0 imm", "BEQ addr"], "preds": [371220], "succs": [371396, 371600], "hash": "636fe48bcdd7eb1ce7af59b0c4128edc"}, "371396": {"disasm": ["LDR R0 [aoffs]", "MOV R2 imm", "STR R2 [R3offs]", "CMP R0 imm", "STR a [R3offs]", "STREQ R3 [aoffs]", "LDRNE R2 [aoffs]", "MOVEQ R0 R3", "STRNE R3 [R2offs]", "ADD R2 R3 imm", "STR R3 [aoffs]", "VST1.32 {D10-D11} [R2]", "BL func", "CMN R0 imm", "MOV R6 R0", "BLT addr"], "preds": [371356], "succs": [371460, 371500], "hash": "6c9da6f948de7c726e15a57e04379686"}, "371460": {"disasm": ["LDR R3 [aoffs]", "MOV R2 imm", "STR R2 [aoffs]", "CMP R3 imm", "BEQ addr"], "preds": [371396], "succs": [371480, 371584], "hash": "a2c7b8ed6c3fe41ab6ac7373975e411f"}, "371480": {"disasm": ["MOV ret a", "ADD SP SP imm", "VPOP {D8-D11}", "POP {a-R7LR}", "BX R3"], "preds": [371460], "succs": [], "hash": "770fac17488b2705d2dbd981d4ad07fc"}, "371500": {"disasm": ["LDR ret [aoffs]", "BL func", "LDR func [aoffs]", "CMP R5 imm", "MOV R7 R0", "BEQ addr"], "preds": [371396], "succs": [371524, 371568], "hash": "02b34617ac3c5d2a78ce792277f873bc"}, "371524": {"disasm": ["MOV R0 R5", "LDR R5 [R5offs]", "LDR R3 [R0offs]", "CMP R3 imm", "BEQ addr"], "preds": [371500, 371548], "succs": [371544, 371548], "hash": "2006f46412b3c5deec74331494f97ec9"}, "371544": {"disasm": ["BLX R3"], "preds": [371524], "succs": [371548], "hash": "6abb72d0cae1fec0cdb4692ebb946762"}, "371548": {"disasm": ["LDR R0 [aoffs]", "BL addr", "CMP R5 imm", "STR R5 [aoffs]", "BNE addr"], "preds": [371524, 371544], "succs": [371524, 371568], "hash": "0573e7a74e44037ab8b670a19b4e5e3c"}, "371568": {"disasm": ["CMP ret r1", "MOV R3 imm", "STR R3 [aoffs]", "MOVGE ret r1"], "preds": [371500, 371548], "succs": [371584], "hash": "777065ad8b59b72aa7800e4c867e46b1"}, "371584": {"disasm": ["MOV R0 R6", "ADD SP SP imm", "VPOP {D8-D11}", "POP {a-R7PC}"], "preds": [371460, 371568, 371600], "succs": [], "hash": "c6952e6d6cce867a4e7c32bf3755e2f0"}, "371600": {"disasm": ["MOV R6 imm", "B addr"], "preds": [371220, 371356], "succs": [371584], "hash": "ec710544738ae4ce21c287b4556881c7"}}}